Workbook

Sheet Quote-R0
A1: Estimate for Renovation Works
C2: Client Address: Tower-A, Ascendas IT Park, Vega, Floor 12, , The V, Plot no 17, Inorbit Mall Rd, Madhapur, Telangana 500081 | E2: Client:
A7: #320, Fifth Floor, East Avenue, fifth floor, VI Phase, Ayyappa Society, Madhapur, Hyderabad, Telangana - 500081, Phone 040-40047888. | C7: Q.No: C2604-110 | E7: Date: 30-04-2026
A8: S.NO. | B8: ITEMS/ DESCRIPTION/ FINISHES | C8: UNIT | D8: QUANTITY | E8: RATE | F8: AMOUNT | H8: material | I8: Service
N9: electrical
B10: Dismantling Work | L10: service | M10: mAterial | N10: interior
A11: 1.1 | B11: Partitions: Dismantling of existing Gypsum/Glass/Wooden partitions wherever required and stacking debris within 10 meters from the work area. Providing and fixing skirting as per site requirement. | C11: Sq.fts | D11: ='Details-R0'!G20 -> 3477.5 | E11: 28 | F11: =E11*D11 -> 97370
A12: 2 | B12: Brick Wall: Dismantling of existing brick wall and lintels where ever necessary and stacking the debris with a lead of 10mts away from the dismantled area and Repairs of the areas. | C12: LS | D12: ='Details-R0'!G24 -> 1 | E12: 10000 | F12: =E12*D12 -> 10000
A13: 2.9 | B13: Column Cladding: Dismantling of existing column cladding wherever required, including stacking of debris within 10 meters from the dismantled area and making good the damaged areas after completion of work. | C13: Sq.fts | D13: ='Details-R0'!G31 -> 750 | E13: 25 | F13: =E13*D13 -> 18750
A14: 3.8 | B14: Wall Paneling: Dismantling of existing wall laminate and paneling wherever required, including stacking of debris within 10 meters from the dismantled area and making good the damaged areas after completion of work. | C14: Sq.fts | D14: ='Details-R0'!G37 -> 507.375 | E14: 27 | F14: =E14*D14 -> 13699.125
A15: 4.7 | B15: False ceiling: Dismantling of existing Gypsum/PVC/Grid false ceiling wherever required, including stacking of debris within 10 meters from the dismantled area and making good the damaged areas after completion of work. | C15: Sq.fts | D15: ='Details-R0'!G54 -> 1391 | E15: 19 | F15: =E15*D15 -> 26429
A16: 5.6 | B16: Furniture: Removing of existing furniture, partitions, wiring, switch boards, etc., and stacking the materials at ground floor as per site requirement. | C16: LS | D16: ='Details-R0'!G58 -> 1 | E16: 250000 | F16: =E16*D16 -> 250000
A17: 6.5 | B17: Carpet: Removing of existing carpet flooring including adhesive residue wherever required, and stacking of debris within 10 meters from the work area as per site instructions. | C17: LS | D17: ='Details-R0'!G66 -> 1 | E17: 30000 | F17: =E17*D17 -> 30000
A18: 8 | B18: Lights: Removing of existing light fittings wherever required and stacking the materials as per site requirement. | C18: LS | D18: ='Details-R0'!G70 -> 1 | E18: 25000 | F18: =E18*D18 -> 25000
A19: 9 | B19: Shifting of debris/materials such as carpet, gypsum material, glass partitions, cabin tables, etc., from 13th floor to ground floor as per site requirement. | C19: LS | D19: ='Details-R0'!G74 -> 1 | E19: 35000 | F19: =E19*D19 -> 35000
A20: 10 | B20: Carting of dismantled debris from the stacked area and disposing the same approximately 10 km away from the site using tractor vehicle. | C20: Load | D20: ='Details-R0'!G78 -> 15 | E20: 5000 | F20: =E20*D20 -> 75000
A21: 11 | B21: Removing of existing doors and door frames and stacking the materials at the location instructed by the site in-charge within 100 meters from the dismantled area. | C21: No's | D21: ='Details-R0'!G88 -> 13 | E21: 2800 | F21: =E21*D21 -> 36400
A22: 12 | B22: Pedestal Removal: Carefully dismantling and removing the existing pedestal from the site, including shifting debris and disposing of waste materials as per site conditions. | C22: LS | D22: 1 | E22: 75000 | F22: =E22*D22 -> 75000 | H22: =137*2*250 -> 68500
B24: Civil Works
A25: 1 | B25: Granite Work
A26: 1.1 | B26: Granite for Counter Top (Pantry Area): Providing and fixing granite countertop with edge polishing and moulding, fixed over plywood/WPC on MS base frame using approved adhesives. The rate includes all materials, hardware, fittings, labour, and installation, complete as per design and instructions of the Architect/Engineer. | C26: Sq.fts | D26: ='Details-R0'!G96 -> 28.5 | E26: 650 | F26: =E26*D26 -> 18525
A27: 2 | B27: Plumbing Works
A28: 2.1 | B28: Plumbing Works Providing and laying of pipeline for pantry connection from 11th floor to ground floor, including all required fittings, supports, cutting, chasing, jointing, testing and fixing complete as per site requirement. | C28: LS | D28: ='Details-R0'!G102 -> 1 | E28: 100000 | F28: =E28*D28 -> 100000 | H28: Installation-1000-2000
A29: 3 | B29: Sanitary Fixtures
A30: 3.1 | B30: SS Sink- 24"X18"X8" - AS per selection | C30: No's | D30: ='Details-R0'!G107 -> 1 | E30: 11500 | F30: =E30*D30 -> 11500 | H30: 8750
A31: 3.2 | B31: Sink Cock : Brand: Parryware/Cera and other accessories | C31: No's | D31: ='Details-R0'!G111 -> 1 | E31: 6500 | F31: =E31*D31 -> 6500 | H31: 1500-1800
A32: 4 | B32: Floor Chipping
A33: 4.1 | B33: Drainage Pipeline: Floor chipping for drain pipeline from pantry room to duct area, including debris removal. Cutting and refixing of metal door for 6" opening as per site requirement. | C33: LS | D33: ='Details-R0'!G115 -> 1 | E33: 20000 | F33: =E33*D33 -> 20000
A34: 5 | B34: Flooring Work
A35: 5.1 | B35: Flooring Work near the entrance: Floor cutting and making new flooring for mat and floor finish, including skirting work at dismantled brick wall area as per site requirement. | C35: LS | D35: ='Details-R0'!G119 -> 1 | E35: 22500 | F35: =E35*D35 -> 22500
A36: 6 | B36: Trap Door
A37: 6.1 | B37: Providing and fixing of trap door including all necessary hardware, fittings and finishing complete as per site requirement. | C37: LS | D37: ='Details-R0'!G123 -> 1 | E37: 4000 | F37: =E37*D37 -> 4000
B39: Modular Glass Works
A40: 1 | B40: Glass Work
A41: 1.1 | B41: Glass Partition - Upto 2100mm height from FFL Supply and installation of 10 mm toughened glass partition (OTIC/Taiton/Dolysia/Ozone or equivalent) in 45 x 25 mm anodized aluminum sections. Ply support to be provided for door frames as required, as per drawings. | C41: Sq.fts | D41: 732 | E41: 520 | F41: =E41*D41 -> 380640 | H41: 385 | I41: 325
A42: 1.2 | B42: Frosted Glass Film: Supply and application of frosted glass film on glass surface, including proper surface cleaning and fixing without bubbles, complete with all materials and labour. | C42: Sq.fts | D42: 522 | E42: 150 | F42: =E42*D42 -> 78300 | H42: 75
A43: 1.3 | B43: Glass Door : Single Leaf Supply and installation of single leaf aluminium stile glass door with 45mm x 45mm frame and 65mm x 35mm shutter, finished in black anodized finish. Door fitted with 10mm thick clear toughened glass and required glass hardware of OTIC/Taiton/Dolysia/Ozone or equivalent, complete as per specifications.
B44: Opening Size : W 900mm X H 2100mm Nos. Per Door | C44: No's | D44: ='Details-R0'!G159 -> 8 | E44: 46800 | F44: =E44*D44 -> 374400 | H44: 29500
A45: 1.4 | B45: Glass Door : Double Leaf Supply and installation of single leaf aluminium stile glass door with 45mm x 45mm frame and 65mm x 35mm shutter, finished in black anodized finish. Door fitted with 10mm thick clear toughened glass and required glass hardware of OTIC/Taiton/Dolysia/Ozone or equivalent, complete as per specifications.
B46: Opening Size : W 2700mm X H 2100mm Nos. Per Door | C46: No's | D46: ='Details-R0'!G163 -> 1 | E46: 97500 | F46: =E46*D46 -> 97500 | H46: =37500+37500 -> 75000
B47: Opening Size : W 1800mm X H 2100mm Nos. Per Door | C47: No's | D47: ='Details-R0'!G167 -> 1 | E47: =E44*2 -> 93600 | F47: =E47*D47 -> 93600
B49: Interior Works
A50: 1 | B50: False Ceiling
A51: 1.1 | B51: Gypsum ceilng : Supply and Installation of 12.5mm thick Saint-Gobain Gypsum Board Suspended Ceiling fixed on proprietary GI steel suspension system (Ultra frames & accessories) as per manufacturer’s recommendations. The work includes screws, joint taping, jointing compound/grout, vertical drops wherever required, and necessary cut-outs for light fixtures, diffusers, grills, etc., complete as per architect’s approved design and manufacturer’s specifications. | C51: Sq.fts/Rfts | D51: ='Details-R0'!G190 -> 4917.9031 | E51: 95 | F51: =E51*D51 -> 467200.8 | H51: 65
A52: 2 | B52: Internal Partitions
A53: 2.1 | B53: Gypsum Partition - 100 mm thick 2 sided double gypsum partition Providing and installing 100 mm thick 2 sided gypsum partition with necessary GI sections and approved Gypsum sheet on either side of the partition with rock wool infill for accoustics. Make: Oman(India) | C53: Sq.fts | D53: ='Details-R0'!G212 -> 1300.65 | E53: 180 | F53: =E53*D53 -> 234117
A54: 2.2 | B54: Ply Panelling Work: Providing and fixing of 18mm plywood panelling for TV and logo support, including necessary framework, fixing and finishing complete as per site requirement. | C54: Sq.fts | D54: ='Details-R0'!G220 -> 225 | E54: 450 | F54: =E54*D54 -> 101250
A55: 3 | B55: Doors
B56: Flush doors: Supply and installation of 30mm thk. Door Opening flushed door finished with 1mm thk. laminate with wooden frame as per approval from both sides with or without vision panel, including wooden beadings for vision panel finished with melamine polish matching the color of laminate, required door hardware(matching the existing) and Aluminum door frames.
A57: 3.1 | B57: Opening Size : W 900mm X H 2100mm Nos. Per Door | C57: No's | D57: ='Details-R0'!G227 -> 2 | E57: 32000 | F57: =E57*D57 -> 64000
A58: 4 | B58: Flooring
A59: 4.1 | B59: Carpet: Supply and installation of Nylon carpet flooring of standard make and approved shade, including adhesives and laying, complete as per design and specifications. | C59: Sq.fts | D59: ='Details-R0'!G246 -> 4181.9375 | E59: 150 | F59: =E59*D59 -> 627290.62
A60: 4.2 | B60: Skirting 50mm wide : Supply and fixing of 50 mm wide aluminum skirting in black color, matching with the flooring, complete in all respects. | C60: Rfts | D60: ='Details-R0'!G271 -> 534.25 | E60: 160 | F60: =E60*D60 -> 85480
A61: 5 | B61: Painting
A62: 5.1 | B62: Painting - Enclosed areas Providing and applying on the walls, ceiling premium emulison painting with required coat of paint. Paint of approved brand and shade as per the specifications of the manufacturer over two coats of putty and primer to achieve smooth and uniform surface and shade. `The rate shall inlcude cleaning and preperation of surface, sanding the surface to smoothness as per the specification or as instructed by Architect including necessary scaffolding, staging, etc,. | C62: Sq.fts | D62: ='Details-R0'!G321 -> 9532.35 | E62: 40 | F62: =E62*D62 -> 381294
A63: 6 | B63: Modular Furniture
A64: 6.1 | B64: Reception Table: Providing supply and fixing of Reception table as per design made in with ply and laminate including cost of all materials labour etc., complete for finished item of work. Size: 1500 L x 750 D x 1050 H | C64: Sq.fts | D64: ='Details-R0'!G327 -> 24 | E64: 3500 | F64: =E64*D64 -> 84000
A65: 6.2 | B65: Conference Table: 11 Pax Specification Size - 4000 (L) x 1200 (D) x 750 (H) Table top 25 mm thick PLPB duly edge bended Support structure 50 x 25 x 1.2 mm rectangular pipe Leg 50 x 50 x 1.2 mm thick tapper leg rectangular pipe duly powder coated. Middle leg 50 x 50 x 1.2 mm thick rectangular pipe with perforated sheet for cable riser duly powder coated Electrical: 2 Nos flapper & metal trunking | C65: No's | D65: ='Details-R0'!G332 -> 1 | E65: 115000 | F65: =E65*D65 -> 115000
A66: 6.3 | B66: Conference Table: 8 Pax Specification Size - 3000 (L) x 1050 (D) x 750 (H) Table top 25 mm thick PLPB duly edge bended Support structure 50 x 25 x 1.2 mm rectangular pipe Leg 50 x 50 x 1.2 mm thick tapper leg rectangular pipe duly powder coated. Middle leg 50 x 50 x 1.2 mm thick rectangular pipe with perforated sheet for cable riser duly powder coated Electrical: 2 Nos flapper & metal trunking | C66: No's | D66: ='Details-R0'!G336 -> 1 | E66: 85450 | F66: =E66*D66 -> 85450
A67: 6.4 | B67: Conference Table: 6 Pax Specification Size - 2400 (L) x 1000 (D) x 750 (H) Table top 25 mm thick PLPB duly edge bended Support structure 50 x 25 x 1.2 mm rectangular pipe Leg 50 x 50 x 1.2 mm thick tapper leg rectangular pipe duly powder coated. Middle leg 50 x 50 x 1.2 mm thick rectangular pipe with perforated sheet for cable riser duly powder coated Electrical: 1 Nos flapper & metal trunking | C67: No's | D67: ='Details-R0'!G341 -> 2 | E67: 45600 | F67: =E67*D67 -> 91200
A68: 6.5 | B68: Manager Cabin table: SIZE: 1450L X 600D X 750H TABLE TOP: 25mm thick PLB with edge band. LEGS: 50X25 mm Square metal legs with power coating. WIRE MANAGEMENT: 350mm flipup. Side storge: 900Wx450Dx690H. with shutter. | C68: No's | D68: ='Details-R0'!G345 -> 1 | E68: 38550 | F68: =E68*D68 -> 38550
A69: 6.6 | B69: Desking Workstation - Sharing size : 1050(w) X 600mm(d) X 750mm(ht) Table Top Made Up Of 25mm Thick PLPB With 2mm PVC Edge Banding MS Powder coated Oval Legs intermidiate 50sq perform legs Wire Manager : Grommet Hole 250mm(ht) Race Way Below Table Top Vertical Wire Entry Main Screen : 12mm thick & 300mm(ht) fabric magnetic board on holders | C69: No's | D69: ='Details-R0'!G350 -> 116 | E69: 9800 | F69: =E69*D69 -> 1136800
A70: 6.7 | B70: Desking Workstation - Non-Sharing size : 1050(w) X 600mm(d) X 750mm(ht) Table Top Made Up Of 25mm Thick PLPB With 2mm PVC Edge Banding MS Powder coated Oval Legs intermidiate 50sq perform legs Wire Manager : Grommet Hole 250mm(ht) Race Way Below Table Top Vertical Wire Entry Main Screen : 12mm thick & 300mm(ht) fabric magnetic board on holders | C70: No's | D70: ='Details-R0'!G356 -> 24 | E70: 11500 | F70: =E70*D70 -> 276000
A71: 6.8 | B71: Desking Workstation -Training Room size : 900(w) X 600mm(d) X 750mm(ht) Table Top Made Up Of 25mm Thick PLPB With 2mm PVC Edge Banding MS Powder coated Oval Legs intermidiate 50sq perform legs Wire Manager : Grommet Hole 250mm(ht) Race Way Below Table Top Vertical Wire Entry Main Screen : 12mm thick & 300mm(ht) | C71: No's | D71: ='Details-R0'!G360 -> 39 | E71: 14500 | F71: =E71*D71 -> 565500 | H71: 7500
A72: 6.9 | B72: Round Table: Specification Size - 900 mm Dia x 750 mm Height Discussion table in particle board table top made of 25 mm thick PLPB .under structure made of 18mm thick PLPB | C72: No's | D72: ='Details-R0'!G365 -> 3 | E72: 15000 | F72: =E72*D72 -> 45000
A73: 6.1 | B73: Speakers Podium: Providing and fixing of speaker podium including necessary framework, finishing and accessories complete as per approved design and site requirement. | C73: No's | D73: ='Details-R0'!G369 -> 1 | E73: 28750 | F73: =E73*D73 -> 28750
A74: 7 | B74: Loose Furniture
A75: 7.1 | B75: Chairs: Supply and instllation of Low Back with Mesh Back: Provides good ventilation and support, keeping you cool and comfortable during long hours of sitting. Knee Tilt (KT) Mechanism: Allows the chair to tilt from just under the knee, which helps keep your feet flat on the floor even when the chair is tilted back. This mechanism offers better support and comfort. Fixed Armrest: Provides consistent support for your arms, reducing strain on your shoulders and neck. Gaslift for Seat Height Adjustment: Enables easy adjustment of the seat height to match your desk height and personal comfort. Standard 5-prong Nylon Base: Offers stability and durability, ensuring the chair remains steady and secure. Additionally, this chair comes with a 10-year warranty, excluding the mesh/fabric components. Model:Fulkrum low Back-KT Series Brand: Merryfair | C75: No's | D75: ='Details-R0'!G384 -> 441 | E75: =10450*1.2 -> 12540 | F75: =E75*D75 -> 5530140
A76: 7.2 | B76: Pantry Chairs: Cafe chair made of PP seat and back | C76: No's | D76: ='Details-R0'!G389 -> 12 | E76: 4500 | F76: =E76*D76 -> 54000
A77: 7.3 | B77: Training Chairs: Supply and instllation of Robo Medium Mesh Back Chair - Black Cushion Seat Centre Tilt Mechanism Lumbar Support Fixed Arms Nylon Base ( As pe the sample) | C77: No's | D77: 39 | E77: =6000*1.2 -> 7200 | F77: =E77*D77 -> 280800
A78: 8 | B78: Wall Paneling
A79: 8.1 | B79: Panelling Works: Providing and fixing fluted wall panels with backing framework, including all materials, labour, and installation, complete. | C79: Sq.fts | D79: ='Details-R0'!G394 -> 198 | E79: 950 | F79: =E79*D79 -> 188100
A80: 8.2 | B80: Laminate Work: Providing and pasting of new laminate on wall surface, including surface preparation, adhesive and finishing complete as per site requirement. | C80: Sq.fts | D80: ='Details-R0'!G400 -> 507.375 | E80: 250 | F80: =E80*D80 -> 126843.75
A81: 8.3 | B81: Acoustic Panels: Providing and fixing 9mm PET acoustic fluted wall panels with aluminium/plywood framing. Including all materials and labour, complete as per drawings and instructions. | C81: Sq.fts | D81: ='Details-R0'!G405 -> 717.75 | E81: 350 | F81: =E81*D81 -> 251212.5
A82: 9 | B82: Ply Deck
B83: 18mm Ply Deck Work: Providing and fixing of 18mm plywood deck with laminate finish, including adhesive, edge finishing, cutting and fixing complete as per site requirement. | C83: Sq.fts | D83: ='Details-R0'!G412 -> 83.25 | E83: 950 | F83: =E83*D83 -> 79087.5
B84: Storage Unit: Providing and fixing storage unit using 18mm thick BWP 710 Grade plywood finished with 1mm thick laminate externally and 1mm thick internal laminate of approved shade, complete as per approved design and site requirements. | C84: Sq.fts | D84: =(10*4)+(17*3) -> 91 | E84: 1800 | F84: =E84*D84 -> 163800
B85: Work Stations Support: Providing and fixing workstation support panel made of PLB board of size 2.5’ x 2.5’, complete with necessary supports and fixing arrangements as per approved design and site requirements. | C85: LS | D85: 1 | E85: 195000 | F85: =E85*D85 -> 195000 | H85: 137 | I85: =H85*70% -> 95.9 | J85: =I85*2 -> 191.8 | K85: =J85*1000 -> 191800
A86: 10 | B86: LOGO
A87: 10.1 | B87: Logo Work: Providing and fixing of logo as per approved design, including fabrication, materials, installation, and finishing. The rate includes all labour, tools, and complete work. Size considered 5' x 4' | C87: LS | D87: 1 | E87: 75000 | F87: =E87*D87 -> 75000
A88: 11 | B88: Wall Paper
A89: 11.1 | B89: Wall Paper: (Customized Wall paper) Providing and fixing designer wallpaper as per approved design, including surface preparation, adhesive, and complete installation at site. | C89: Sq.fts | D89: ='Details-R0'!G422 -> 486 | E89: 250 | F89: =E89*D89 -> 121500 | H89: 13392294
A90: 12 | B90: Laquered Glass
A91: 12.1 | B91: Supply and fixing of laquered glass 6mm thick over ply panelling of 12mm thick including cost of all materials labour transport etc., complete. 6no's X6'X4' | C91: Sq.fts | D91: ='Details-R0'!G426 -> 144 | E91: 650 | F91: =E91*D91 -> 93600
A92: 13 | B92: Blinds in Training Room
A93: 13.1 | B93: Window Roller Blinds: Supply and installation of window roller blinds with aluminium headrail and fabric, custom-made as per window size. Suitable for classrooms and office windows. Complete with all fittings and accessories. | C93: Sq.fts | D93: ='Details-R0'!G430 -> 276 | E93: 200 | F93: =E93*D93 -> 55200
A94: 14 | B94: Storage Shutter Work
A95: 14.1 | B95: Adjustment and alignment of existing storage shutters including necessary fittings and smooth operation complete as per site requirement. | C95: LS | D95: ='Details-R0'!G434 -> 1 | E95: 20000 | F95: =E95*D95 -> 20000
A96: 15 | B96: Electrical Works- Main wiring
A97: 15.1 | B97: Providing, supplying, and fixing of electrical wiring for the complete office space, including cost of wires, switches, sockets, and all accessories. Complete for finished item of work as per standards and specifications designed by the electrical engineer, including all materials and labour charges. (Price may vary as per site conditions and scope of work.) | C97: LS | D97: ='Details-R0'!G438 -> 1 | E97: 2541500 | F97: =E97*D97 -> 2541500 | G97: 743030
A98: 16 | B98: HVAC
A99: 16.1 | B99: Supply Installation and Testing commissioning of AC works for the said project Toshiba, Works includes VRV system-28 Hp-10 ODU and Cassete for conference rooms and Work Station area, Split AC's Cabin and Discussion Rooms, Copper pipe, communication cable with individual units remotes.(Price may vary as per site conditions and scope of work.) | C99: LS | D99: ='Details-R0'!G442 -> 1 | E99: 1799460 | F99: =E99*D99 -> 1799460
A100: 17 | B100: FA, PA, RRS, WLDS
A101: 17.1 | B101: Providing, fixing and commissioning of Fire alarm System, Public address System, Rodent Repellent System and including all necessary accessories, wiring and testing complete as per site requirement. | C101: LS | D101: ='Details-R0'!G446 -> 1 | E101: 2690170 | F101: =E101*D101 -> 2690170
A102: 19 | B102: AV System
A103: 19.1 | B103: Providing and installation of AV system for training room including Interactive Screen brand BENQ Size: 86", Ahuja speakers, HDMI points, wiring and necessary accessories complete as per site requirement. | C103: LS | D103: ='Details-R0'!G454 -> 1 | E103: =375000+235000 -> 610000 | F103: =E103*D103 -> 610000
A104: 20 | B104: Deep Cleaning Work
A105: 20.1 | B105: Complete deep cleaning of floors, walls, windows, furniture and work areas using suitable cleaning materials and equipment, including shampoo wash at required locations. | C105: LS | D105: 1 | E105: 350000 | F105: =E105*D105 -> 350000
A106: 21 | B106: HouseKeeping Work
A107: 21.1 | B107: Regular cleaning and maintenance of floor, workstations, and common areas by housekeeping staff using necessary cleaning materials and tools. | C107: LS | D107: 1 | E107: 80000 | F107: =E107*D107 -> 80000 | H107: 8364930
...

Sheet Details-R0
A1: S.No | B1: Description | C1: Units | D1: No's | E1: L | F1: W | G1: Qty
B3: Dismantling
B4: Paritions
B5: Reception Area | C5: Sqfts | D5: 1 | E5: 5.5 | F5: 10 | G5: =F5*E5*D5 -> 55
C6: Sqfts | D6: 1 | E6: 25.5 | F6: 10 | G6: =F6*E6*D6 -> 255
C7: Sqfts | D7: 1 | E7: 18 | F7: 10 | G7: =F7*E7*D7 -> 180
C8: Sqfts | D8: 1 | E8: 25.75 | F8: 10 | G8: =F8*E8*D8 -> 257.5
B9: Travel Desk/Visiting Dir | C9: Sqfts | D9: 2 | E9: 11.25 | F9: 10 | G9: =F9*E9*D9 -> 225
C10: Sqfts | D10: 2 | E10: 22.25 | F10: 10 | G10: =F10*E10*D10 -> 445
B11: Interview Rooms | C11: Sqfts | D11: 2 | E11: 11.25 | F11: 10 | G11: =F11*E11*D11 -> 225
C12: Sqfts | D12: 2 | E12: 18.25 | F12: 10 | G12: =F12*E12*D12 -> 365
B13: Cabins | C13: Sqfts | D13: 3 | E13: 11.25 | F13: 10 | G13: =F13*E13*D13 -> 337.5
C14: Sqfts | D14: 2 | E14: 26.25 | F14: 10 | G14: =F14*E14*D14 -> 525
B15: Utility Beside Room | C15: Sqfts | D15: 1 | E15: 9.5 | F15: 10 | G15: =F15*E15*D15 -> 95
B16: 8Pax Conference Room | C16: Sqfts | D16: 1 | E16: 10.75 | F16: 10 | G16: =F16*E16*D16 -> 107.5
B17: Conference Room | C17: Sqfts | D17: 1 | E17: 27.5 | F17: 10 | G17: =F17*E17*D17 -> 275
C18: Sqfts | D18: 1 | E18: 13 | F18: 10 | G18: =F18*E18*D18 -> 130
B20: TOTAL | G20: =SUM(G5:G19) -> 3477.5
B21: Brick Wall
B22: Reception Area | C22: Sqfts | D22: 1 | E22: 5.5 | F22: 10 | G22: =F22*E22*D22 -> 55
B24: TOTAL | G24: 1
B25: Columns
B26: Reception Area | C26: Sqfts | D26: 8 | E26: 2.5 | F26: 10 | G26: =F26*E26*D26 -> 200
C27: Sqfts | D27: 8 | E27: 2.5 | F27: 10 | G27: =F27*E27*D27 -> 200
C28: Sqfts | D28: 7 | E28: 2.5 | F28: 10 | G28: =F28*E28*D28 -> 175
C29: Sqfts | D29: 7 | E29: 2.5 | F29: 10 | G29: =F29*E29*D29 -> 175
B31: TOTAL | G31: =SUM(G26:G30) -> 750
B32: Wall Panelling
B33: Linear Work Station Area | C33: Sqfts | D33: 1 | E33: 4 | F33: 8.25 | G33: =F33*E33*D33 -> 33
C34: Sqfts | D34: 1 | E34: 51.5 | F34: 8.25 | G34: =F34*E34*D34 -> 424.875
B35: Linear Work Station Area-Corridor | C35: Sqfts | D35: 1 | E35: 6 | F35: 8.25 | G35: =F35*E35*D35 -> 49.5
B37: TOTAL | G37: =SUM(G33:G36) -> 507.375
B38: False Ceiling
B39: Reception Area | C39: Sqfts | D39: 1 | E39: 5.5 | F39: 4 | G39: =F39*E39*D39 -> 22
C40: Sqfts | D40: 1 | E40: 25.5 | F40: 4 | G40: =F40*E40*D40 -> 102
C41: Sqfts | D41: 1 | E41: 18 | F41: 4 | G41: =F41*E41*D41 -> 72
C42: Sqfts | D42: 1 | E42: 25.75 | F42: 4 | G42: =F42*E42*D42 -> 103
B43: Travel Desk/Visiting Dir | C43: Sqfts | D43: 2 | E43: 11.25 | F43: 4 | G43: =F43*E43*D43 -> 90
C44: Sqfts | D44: 2 | E44: 22.25 | F44: 4 | G44: =F44*E44*D44 -> 178
B45: Interview Rooms | C45: Sqfts | D45: 2 | E45: 11.25 | F45: 4 | G45: =F45*E45*D45 -> 90
C46: Sqfts | D46: 2 | E46: 18.25 | F46: 4 | G46: =F46*E46*D46 -> 146
B47: Cabins | C47: Sqfts | D47: 3 | E47: 11.25 | F47: 4 | G47: =F47*E47*D47 -> 135
C48: Sqfts | D48: 2 | E48: 26.25 | F48: 4 | G48: =F48*E48*D48 -> 210
B49: Utility Beside Room | C49: Sqfts | D49: 1 | E49: 9.5 | F49: 4 | G49: =F49*E49*D49 -> 38
B50: 8Pax Conference Room | C50: Sqfts | D50: 1 | E50: 10.75 | F50: 4 | G50: =F50*E50*D50 -> 43
B51: Conference Room | C51: Sqfts | D51: 1 | E51: 27.5 | F51: 4 | G51: =F51*E51*D51 -> 110
C52: Sqfts | D52: 1 | E52: 13 | F52: 4 | G52: =F52*E52*D52 -> 52
B54: TOTAL | G54: =SUM(G39:G53) -> 1391
B55: Furniture
B56: Office | C56: Sqfts | D56: 1 | E56: 1 | F56: 1 | G56: =F56*E56*D56 -> 1
B58: TOTAL | G58: =SUM(G56:G57) -> 1
B59: Carpet
B60: Travel Desk/Visiting Dir | C60: Sqfts | D60: 1 | E60: 21.75 | F60: 11.25 | G60: =F60*E60*D60 -> 244.6875
B61: Interview Rooms | C61: Sqfts | D61: 1 | E61: 11.5 | F61: 18 | G61: =F61*E61*D61 -> 207
B62: Cabins | C62: Sqfts | D62: 1 | E62: 26 | F62: 10.75 | G62: =F62*E62*D62 -> 279.5
B63: Conference Room | C63: Sqfts | D63: 1 | E63: 17.75 | F63: 10.75 | G63: =F63*E63*D63 -> 190.8125
B64: Training Room | C64: Sqfts | D64: 1 | E64: 1172 | F64: 1 | G64: =F64*E64*D64 -> 1172
B66: TOTAL | G66: 1
B67: Lights
B68: Office | C68: Sqfts | D68: 1 | E68: 1 | F68: 1 | G68: =F68*E68*D68 -> 1
B70: TOTAL | G70: =SUM(G68:G69) -> 1
B71: Shifting
B72: Office | C72: Sqfts | D72: 1 | E72: 1 | F72: 1 | G72: =F72*E72*D72 -> 1
B74: TOTAL | G74: =SUM(G72:G73) -> 1
B75: Load
B76: Office | C76: Sqfts | D76: 15 | E76: 1 | F76: 1 | G76: =F76*E76*D76 -> 15
B78: TOTAL | G78: =SUM(G76:G77) -> 15
B79: Doors
B80: Entry Door | C80: No's | D80: 1 | E80: 1 | F80: 1 | G80: =F80*E80*D80 -> 1
B81: Travel Desk/Visiting Dir | C81: No's | D81: 2 | E81: 1 | F81: 1 | G81: =F81*E81*D81 -> 2
B82: Interview Rooms | C82: No's | D82: 2 | E82: 1 | F82: 1 | G82: =F82*E82*D82 -> 2
B83: Cabins | C83: No's | D83: 3 | E83: 1 | F83: 1 | G83: =F83*E83*D83 -> 3
B84: Utility Beside Room | C84: No's | D84: 1 | E84: 1 | F84: 1 | G84: =F84*E84*D84 -> 1
B85: Conference Room | C85: No's | D85: 1 | E85: 1 | F85: 1 | G85: =F85*E85*D85 -> 1
B86: 8Pax Conference Room | C86: No's | D86: 3 | E86: 1 | F86: 1 | G86: =F86*E86*D86 -> 3
B88: TOTAL | G88: =SUM(G80:G87) -> 13
B90: Civil Work
A92: 1 | B92: Granite Work
B93: Pantry
B94: Pantry | C94: Sqfts | D94: 1 | E94: 14.25 | F94: 2 | G94: =F94*E94*D94 -> 28.5
B96: TOTAL | G96: =SUM(G94:G95) -> 28.5
A99: 2 | B99: Plumbing Works
B100: Pantry | C100: Sqfts | D100: 1 | E100: 1 | F100: 1 | G100: =F100*E100*D100 -> 1
B102: TOTAL | G102: =SUM(G100:G101) -> 1
A103: 3.1 | B103: Sanitary Fixtures
B104: SS Sink
B105: Pantry | C105: Sqfts | D105: 1 | E105: 1 | F105: 1 | G105: =F105*E105*D105 -> 1
B107: TOTAL | G107: =SUM(G105:G106) -> 1
A108: 3.2 | B108: Sink Cock
B109: Pantry | C109: Sqfts | D109: 1 | E109: 1 | F109: 1 | G109: =F109*E109*D109 -> 1
B111: TOTAL | G111: =SUM(G109:G110) -> 1
A112: 4 | B112: Floor Chipping
B113: Pantry | C113: Sqfts | D113: 1 | E113: 1 | F113: 1 | G113: =F113*E113*D113 -> 1
B115: TOTAL | G115: =SUM(G113:G114) -> 1
A116: 5 | B116: Flooring Work
B117: Entrance | C117: Sqfts | D117: 1 | E117: 1 | F117: 1 | G117: =F117*E117*D117 -> 1
B119: TOTAL | G119: =SUM(G117:G118) -> 1
A120: 6 | B120: Trap door
B121: Entrance | C121: Sqfts | D121: 1 | E121: 1 | F121: 1 | G121: =F121*E121*D121 -> 1
B123: TOTAL | G123: =SUM(G121:G122) -> 1
...
